cadule.py
cadule-0.0.1.dist-info/licenses/LICENSE
cadule-0.0.1.dist-info/METADATA
cadule-0.0.1.dist-info/WHEEL
cadule-0.0.1.dist-info/top_level.txt
cadule-0.0.1.dist-info/RECORD
