Metadata-Version: 2.4
Name: cadule
Version: 0.0.1
Summary: A Python library that provides decorators for converting regular modules into callable modules
Author-email: AN Long <aisk1988@gmail.com>
Maintainer-email: AN Long <aisk1988@gmail.com>
License: BSD-3-Clause
Keywords: python,decorator,metaprogramming,module,callable
Classifier: Development Status :: 3 - Alpha
Classifier: Intended Audience :: Developers
Classifier: License :: OSI Approved :: BSD License
Classifier: Operating System :: OS Independent
Classifier: Programming Language :: Python :: 3
Classifier: Programming Language :: Python :: 3.8
Classifier: Programming Language :: Python :: 3.9
Classifier: Programming Language :: Python :: 3.10
Classifier: Programming Language :: Python :: 3.11
Classifier: Programming Language :: Python :: 3.12
Classifier: Programming Language :: Python :: 3.13
Classifier: Programming Language :: Python :: 3 :: Only
Classifier: Topic :: Software Development :: Libraries :: Python Modules
Classifier: Topic :: Software Development :: Code Generators
Requires-Python: >=3.8
License-File: LICENSE
Dynamic: license-file
